{
  "users": [
    {
      "id": 1,
      "email": "minsu@test.com",
      "password": "1234",
      "nickname": "민수"
    },
    {
      "id": 2,
      "email": "jiyeon@test.com",
      "password": "1234",
      "nickname": "지연"
    },
    {
      "id": 3,
      "email": "dongho@test.com",
      "password": "1234",
      "nickname": "동호"
    },
    {
      "email": "new@test.com",
      "password": "1234",
      "nickname": "새사용자",
      "id": 4
    }
  ],
  "transactions": [
    {
      "id": 1,
      "userId": 1,
      "type": "INCOME",
      "category": "기타",
      "amount": 3000000,
      "memo": "월급",
      "date": "2026-04-01"
    },
    {
      "id": 2,
      "userId": 1,
      "type": "EXPENSE",
      "category": "식비",
      "amount": 12000,
      "memo": "점심 식사",
      "date": "2026-04-02"
    },
    {
      "id": 3,
      "userId": 2,
      "type": "EXPENSE",
      "category": "교통",
      "amount": 2500,
      "memo": "버스",
      "date": "2026-04-02"
    }
  ],
  "couples": [
    {
      "id": 1,
      "user1Id": 1,
      "user2Id": 2,
      "status": true,
      "createdAt": "2026-04-01"
    }
  ],
  "coupleRequests": [
    {
      "id": 1,
      "fromId": 2,
      "toId": 1,
      "status": "pending",
      "createdAt": "2026-04-07"
    },
    {
      "id": 2,
      "fromId": 3,
      "toId": 1,
      "status": "rejected",
      "createdAt": "2026-04-07"
    }
  ]
}
